[
  {
    "__type__": "cc.Prefab",
    "_name": "WinOptimize1",
    "_objFlags": 0,
    "_native": "",
    "data": {
      "__id__": 1
    },
    "optimizationPolicy": 0,
    "asyncLoadAssets": false,
    "readonly": false
  },
  {
    "__type__": "cc.Node",
    "_name": "WinOptimize",
    "_objFlags": 0,
    "_parent": null,
    "_children": [
      {
        "__id__": 3
      },
      {
        "__id__": 6
      },
      {
        "__id__": 12
      }
    ],
    "_active": true,
    "_components": [
      {
        "__id__": 15
      }
    ],
    "_prefab": {
      "__id__": 2
    },
    "_opacity": 255,
    "_color": {
      "__type__": "cc.Color",
      "r": 255,
      "g": 255,
      "b": 255,
      "a": 255
    },
    "_contentSize": {
      "__type__": "cc.Size",
      "width": 1080,
      "height": 1920
    },
    "_anchorPoint": {
      "__type__": "cc.Vec2",
      "x": 0.5,
      "y": 0.5
    },
    "_trs": {
      "__type__": "TypedArray",
      "ctor": "Float64Array",
      "array": [
        540,
        960,
        0,
        0,
        0,
        0,
        1,
        1,
        1,
        1
      ]
    },
    "_eulerAngles": {
      "__type__": "cc.Vec3",
      "x": 0,
      "y": 0,
      "z": 0
    },
    "_skewX": 0,
    "_skewY": 0,
    "_is3DNode": false,
    "_groupIndex": 0,
    "groupIndex": 0,
    "_id": ""
  },
  {
    "__type__": "cc.PrefabInfo",
    "root": {
      "__id__": 1
    },
    "asset": {
      "__uuid__": "91f1dd56-fe0e-4d77-9d36-d6aefdc53fc9"
    },
    "fileId": "",
    "sync": false
  },
  {
    "__type__": "cc.Node",
    "_name": "spine_victory",
    "_objFlags": 0,
    "_parent": {
      "__id__": 1
    },
    "_children": [],
    "_active": true,
    "_components": [
      {
        "__id__": 5
      }
    ],
    "_prefab": {
      "__id__": 4
    },
    "_opacity": 255,
    "_color": {
      "__type__": "cc.Color",
      "r": 255,
      "g": 255,
      "b": 255,
      "a": 255
    },
    "_contentSize": {
      "__type__": "cc.Size",
      "width": 1384.25,
      "height": 1670.25
    },
    "_anchorPoint": {
      "__type__": "cc.Vec2",
      "x": 0.5,
      "y": 0.5
    },
    "_trs": {
      "__type__": "TypedArray",
      "ctor": "Float64Array",
      "array": [
        0,
        485,
        0,
        0,
        0,
        0,
        1,
        1,
        1,
        1
      ]
    },
    "_eulerAngles": {
      "__type__": "cc.Vec3",
      "x": 0,
      "y": 0,
      "z": 0
    },
    "_skewX": 0,
    "_skewY": 0,
    "_is3DNode": false,
    "_groupIndex": 0,
    "groupIndex": 0,
    "_id": ""
  },
  {
    "__type__": "cc.PrefabInfo",
    "root": {
      "__id__": 1
    },
    "asset": {
      "__uuid__": "91f1dd56-fe0e-4d77-9d36-d6aefdc53fc9"
    },
    "fileId": "3cqASiKcVPYq4INdzVNDxe",
    "sync": false
  },
  {
    "__type__": "sp.Skeleton",
    "_name": "",
    "_objFlags": 0,
    "node": {
      "__id__": 3
    },
    "_enabled": true,
    "_materials": [
      {
        "__uuid__": "7afd064b-113f-480e-b793-8817d19f63c3"
      }
    ],
    "paused": false,
    "defaultSkin": "default",
    "defaultAnimation": "in_1",
    "_preCacheMode": 1,
    "_cacheMode": 1,
    "loop": true,
    "premultipliedAlpha": false,
    "timeScale": 1,
    "_accTime": 0,
    "_playCount": 0,
    "_frameCache": null,
    "_curFrame": null,
    "_skeletonCache": null,
    "_animationName": "in_1",
    "_animationQueue": [],
    "_headAniInfo": null,
    "_playTimes": 0,
    "_isAniComplete": true,
    "_N$skeletonData": {
      "__uuid__": "0bdf502b-a68c-4cb6-adca-1d42b9997153"
    },
    "_N$_defaultCacheMode": 0,
    "_N$debugSlots": false,
    "_N$debugBones": false,
    "_N$debugMesh": false,
    "_N$useTint": false,
    "_N$enableBatch": false,
    "_id": ""
  },
  {
    "__type__": "cc.Node",
    "_name": "lb_title_opt",
    "_objFlags": 0,
    "_parent": {
      "__id__": 1
    },
    "_children": [],
    "_active": true,
    "_components": [
      {
        "__id__": 8
      },
      {
        "__id__": 9
      },
      {
        "__id__": 10
      },
      {
        "__id__": 11
      }
    ],
    "_prefab": {
      "__id__": 7
    },
    "_opacity": 255,
    "_color": {
      "__type__": "cc.Color",
      "r": 255,
      "g": 255,
      "b": 255,
      "a": 255
    },
    "_contentSize": {
      "__type__": "cc.Size",
      "width": 651.69,
      "height": 189
    },
    "_anchorPoint": {
      "__type__": "cc.Vec2",
      "x": 0.5,
      "y": 0.5
    },
    "_trs": {
      "__type__": "TypedArray",
      "ctor": "Float64Array",
      "array": [
        0,
        487.932,
        0,
        0,
        0,
        0,
        1,
        1,
        1,
        1
      ]
    },
    "_eulerAngles": {
      "__type__": "cc.Vec3",
      "x": 0,
      "y": 0,
      "z": 0
    },
    "_skewX": 0,
    "_skewY": 0,
    "_is3DNode": false,
    "_groupIndex": 0,
    "groupIndex": 0,
    "_id": ""
  },
  {
    "__type__": "cc.PrefabInfo",
    "root": {
      "__id__": 1
    },
    "asset": {
      "__uuid__": "91f1dd56-fe0e-4d77-9d36-d6aefdc53fc9"
    },
    "fileId": "97i2Zg43FM77sobjMrSzC8",
    "sync": false
  },
  {
    "__type__": "cc.Label",
    "_name": "",
    "_objFlags": 0,
    "node": {
      "__id__": 6
    },
    "_enabled": true,
    "_materials": [
      {
        "__uuid__": "56af84db-9cd1-4adb-b4d8-48ff7df5b549"
      }
    ],
    "_srcBlendFactor": 770,
    "_dstBlendFactor": 771,
    "_string": "Well Done!",
    "_N$string": "Well Done!",
    "_fontSize": 110,
    "_lineHeight": 150,
    "_enableWrapText": true,
    "_N$file": {
      "__uuid__": "03118851-06e5-48bd-91b8-d11738026110"
    },
    "_isSystemFontUsed": false,
    "_spacingX": 1,
    "_batchAsBitmap": false,
    "_styleFlags": 0,
    "_underlineHeight": 0,
    "_N$horizontalAlign": 1,
    "_N$verticalAlign": 1,
    "_N$fontFamily": "Arial",
    "_N$overflow": 0,
    "_N$cacheMode": 0,
    "_id": ""
  },
  {
    "__type__": "02873PruAdMwKClUvpYAroi",
    "_name": "",
    "_objFlags": 0,
    "node": {
      "__id__": 6
    },
    "_enabled": true,
    "_id": "",
    "__scriptAsset": false,
    "_lightRadius": 10,
    "_lightOpaque": 2,
    "_lightColor": {
      "__type__": "cc.Color",
      "r": 160,
      "g": 70,
      "b": 14,
      "a": 255
    },
    "_offset": {
      "__type__": "cc.Vec2",
      "x": 0,
      "y": 0
    },
    "_lightAlphaThreshold": 1
  },
  {
    "__type__": "c9f6af5intNl6QHSe43NvJk",
    "_name": "",
    "_objFlags": 0,
    "node": {
      "__id__": 6
    },
    "_enabled": true,
    "_id": "",
    "__scriptAsset": false,
    "_colors": [
      {
        "__type__": "cc.Color",
        "r": 251,
        "g": 230,
        "b": 92,
        "a": 255
      },
      {
        "__type__": "cc.Color",
        "r": 251,
        "g": 230,
        "b": 92,
        "a": 255
      },
      {
        "__type__": "cc.Color",
        "r": 245,
        "g": 195,
        "b": 61,
        "a": 255
      },
      {
        "__type__": "cc.Color",
        "r": 245,
        "g": 195,
        "b": 61,
        "a": 255
      }
    ]
  },
  {
    "__type__": "e6a65fFQGtNlZN3E71nPtfJ",
    "_name": "",
    "_objFlags": 0,
    "node": {
      "__id__": 6
    },
    "_enabled": true,
    "_id": "",
    "__scriptAsset": false,
    "translateId": "MahjongTiles_GameEnd_Name_3_2",
    "defaultText": "Well Done"
  },
  {
    "__type__": "cc.Node",
    "_name": "spine_score",
    "_objFlags": 0,
    "_parent": {
      "__id__": 1
    },
    "_children": [],
    "_active": true,
    "_components": [
      {
        "__id__": 14
      }
    ],
    "_prefab": {
      "__id__": 13
    },
    "_opacity": 255,
    "_color": {
      "__type__": "cc.Color",
      "r": 255,
      "g": 255,
      "b": 255,
      "a": 255
    },
    "_contentSize": {
      "__type__": "cc.Size",
      "width": 0,
      "height": 0
    },
    "_anchorPoint": {
      "__type__": "cc.Vec2",
      "x": 0.5,
      "y": 0.5
    },
    "_trs": {
      "__type__": "TypedArray",
      "ctor": "Float64Array",
      "array": [
        0,
        129.377,
        0,
        0,
        0,
        0,
        1,
        1,
        1,
        1
      ]
    },
    "_eulerAngles": {
      "__type__": "cc.Vec3",
      "x": 0,
      "y": 0,
      "z": 0
    },
    "_skewX": 0,
    "_skewY": 0,
    "_is3DNode": false,
    "_groupIndex": 0,
    "groupIndex": 0,
    "_id": ""
  },
  {
    "__type__": "cc.PrefabInfo",
    "root": {
      "__id__": 1
    },
    "asset": {
      "__uuid__": "91f1dd56-fe0e-4d77-9d36-d6aefdc53fc9"
    },
    "fileId": "31xjc/N7VM46NdTFs6+yDv",
    "sync": false
  },
  {
    "__type__": "sp.Skeleton",
    "_name": "",
    "_objFlags": 0,
    "node": {
      "__id__": 12
    },
    "_enabled": true,
    "_materials": [
      {
        "__uuid__": "7afd064b-113f-480e-b793-8817d19f63c3"
      }
    ],
    "paused": false,
    "defaultSkin": "default",
    "defaultAnimation": "in_2",
    "_preCacheMode": 1,
    "_cacheMode": 1,
    "loop": false,
    "premultipliedAlpha": false,
    "timeScale": 1,
    "_accTime": 0,
    "_playCount": 0,
    "_frameCache": null,
    "_curFrame": null,
    "_skeletonCache": null,
    "_animationName": "in_2",
    "_animationQueue": [],
    "_headAniInfo": null,
    "_playTimes": 1,
    "_isAniComplete": true,
    "_N$skeletonData": {
      "__uuid__": "0bdf502b-a68c-4cb6-adca-1d42b9997153"
    },
    "_N$_defaultCacheMode": 0,
    "_N$debugSlots": false,
    "_N$debugBones": false,
    "_N$debugMesh": false,
    "_N$useTint": false,
    "_N$enableBatch": false,
    "_id": ""
  },
  {
    "__type__": "cc.Widget",
    "_name": "",
    "_objFlags": 0,
    "node": {
      "__id__": 1
    },
    "_enabled": true,
    "alignMode": 2,
    "_target": null,
    "_alignFlags": 45,
    "_left": 0,
    "_right": 0,
    "_top": 0,
    "_bottom": 0,
    "_verticalCenter": 0,
    "_horizontalCenter": 0,
    "_isAbsLeft": true,
    "_isAbsRight": true,
    "_isAbsTop": true,
    "_isAbsBottom": true,
    "_isAbsHorizontalCenter": true,
    "_isAbsVerticalCenter": true,
    "_originalWidth": 0,
    "_originalHeight": 0,
    "_id": ""
  },
  {
    "__type__": "cc.PrefabInfo",
    "root": {
      "__id__": 1
    },
    "asset": {
      "__uuid__": "91f1dd56-fe0e-4d77-9d36-d6aefdc53fc9"
    },
    "fileId": "",
    "sync": false
  }
]