{"skeleton":{"hash":"YpFu27uJWwgzHpJ0IWtsfq5C23Y","spine":"3.8.99","x":-265.79,"y":-274.35,"width":530,"height":530},"bones":[{"name":"root"},{"name":"bone2","parent":"root"},{"name":"zong","parent":"root"},{"name":"zong2","parent":"zong","x":-9.07,"y":18.34},{"name":"xia","parent":"zong2","x":9.39,"y":-44.85},{"name":"hou","parent":"zong2","x":-28.43,"y":74.95},{"name":"5","parent":"hou","length":123.84,"rotation":85.03,"x":12.64,"y":-83.59},{"name":"shang","parent":"zong2","x":11.28,"y":9.07,"scaleX":0.7483,"scaleY":0.7483},{"name":"hou2","parent":"zong2","x":-39.98,"y":92.21},{"name":"bone3","parent":"hou2","length":196.99,"rotation":95.44,"x":29.49,"y":-77.9},{"name":"4","parent":"shang","length":137.02,"rotation":-43.73,"x":-19.24,"y":37.05},{"name":"eff","parent":"bone2"},{"name":"light","parent":"eff"},{"name":"bone","parent":"eff","x":-0.79,"y":-9.35},{"name":"lizi","parent":"eff","x":-87.38,"y":15.22},{"name":"lizi3","parent":"lizi","x":10.01,"y":-55.6},{"name":"lizi5","parent":"lizi","x":-0.85,"y":-0.38},{"name":"lizi6","parent":"lizi","x":82.86,"y":65.24},{"name":"lizi7","parent":"lizi","x":37.13,"y":76.8},{"name":"lizi8","parent":"lizi","x":82.86,"y":65.24},{"name":"lizi9","parent":"lizi","x":82.86,"y":65.24},{"name":"eff2","parent":"eff"},{"name":"yf","parent":"bone2"},{"name":"yf2","parent":"yf","x":92.35,"y":94.28,"scaleX":0.815,"scaleY":0.815,"transform":"noScale"},{"name":"yf3","parent":"yf","x":92.35,"y":94.28,"scaleX":0.815,"scaleY":0.815,"transform":"noScale"},{"name":"yf4","parent":"yf","x":92.35,"y":94.28,"scaleX":0.815,"scaleY":0.815,"transform":"noScale"},{"name":"yf5","parent":"yf","x":92.35,"y":94.28,"scaleX":0.815,"scaleY":0.815,"transform":"noScale"},{"name":"yf6","parent":"yf","x":92.35,"y":94.28,"scaleX":0.815,"scaleY":0.815,"transform":"noScale"},{"name":"yf7","parent":"yf","x":92.35,"y":94.28,"scaleX":0.815,"scaleY":0.815,"transform":"noScale"},{"name":"yf8","parent":"yf","x":92.35,"y":94.28,"scaleX":0.815,"scaleY":0.815,"transform":"noScale"},{"name":"yf9","parent":"yf","x":92.35,"y":94.28,"scaleX":0.815,"scaleY":0.815,"transform":"noScale"},{"name":"yf10","parent":"yf","x":92.35,"y":94.28,"scaleX":0.815,"scaleY":0.815,"transform":"noScale"},{"name":"yf11","parent":"yf","x":92.35,"y":94.28,"scaleX":0.815,"scaleY":0.815,"transform":"noScale"},{"name":"lizi10","parent":"lizi","x":-0.85,"y":-0.38},{"name":"xia2","parent":"xia"},{"name":"xia3","parent":"xia"},{"name":"xia4","parent":"xia"}],"slots":[{"name":"mj_12","bone":"bone","attachment":"mj_12"},{"name":"mj_13","bone":"bone","attachment":"mj_12","blend":"additive"},{"name":"mxg/1a3","bone":"yf3"},{"name":"blast_13","bone":"light"},{"name":"blast_14","bone":"light","blend":"additive"},{"name":"5","bone":"5"},{"name":"3","bone":"xia","attachment":"3"},{"name":"7","bone":"xia","attachment":"3","blend":"additive"},{"name":"4","bone":"shang","attachment":"4"},{"name":"6","bone":"bone3"},{"name":"mj1212","bone":"xia2","blend":"additive"},{"name":"mj1213","bone":"xia4","blend":"additive"},{"name":"mj_4","bone":"lizi3","attachment":"mj_3"},{"name":"mj_14","bone":"lizi6","attachment":"mj_3"},{"name":"mj_17","bone":"lizi9","attachment":"mj_3"},{"name":"mj_16","bone":"lizi8","attachment":"mj_3"},{"name":"mj_15","bone":"lizi7","attachment":"mj_3"},{"name":"mj_9","bone":"lizi5","attachment":"mj_3"},{"name":"mj_10","bone":"lizi10","attachment":"mj_3"},{"name":"mxg/1a15","bone":"yf9"},{"name":"blast_12","bone":"eff2","blend":"additive"},{"name":"mxg/1a","bone":"yf2"},{"name":"mxg/1a5","bone":"yf4"},{"name":"mxg/1a7","bone":"yf5"},{"name":"mxg/1a17","bone":"yf10"},{"name":"mxg/1a9","bone":"yf6"},{"name":"mxg/1a11","bone":"yf7"},{"name":"mxg/1a13","bone":"yf8"},{"name":"mxg/1a14","bone":"yf11"},{"name":"blast_122","bone":"xia3","blend":"additive"}],"skins":[{"name":"default","attachments":{"3":{"3":{"width":228,"height":195}},"4":{"4":{"type":"mesh","hull":33,"uvs":[0.62724,0.08907,0.71075,0.09932,0.7831,0.12338,0.84473,0.17149,0.88671,0.23732,0.90279,0.30822,0.89484,0.64927,0.88103,0.68787,0.86051,0.74347,0.82879,0.80417,0.7956,0.86415,0.75165,0.90606,0.68274,0.90631,0.61339,0.90453,0.53465,0.89669,0.41714,0.87693,0.36597,0.86275,0.29809,0.83997,0.2445,0.81718,0.19805,0.78806,0.1609,0.75718,0.13021,0.71746,0.10248,0.66525,0.10166,0.39978,0.10802,0.33694,0.15125,0.27883,0.21832,0.23276,0.29532,0.20997,0.35775,0.20301,0.4151,0.20795,0.44331,0.17252,0.48842,0.13312,0.54677,0.10235,0.11677,0.45762,0.15657,0.51407,0.21055,0.55131,0.26001,0.58045,0.31038,0.60324,0.36368,0.62171,0.42855,0.6369,0.50085,0.64753,0.58034,0.66145,0.64003,0.66398,0.70075,0.66512,0.75362,0.66398,0.79471,0.61714,0.82508,0.5703,0.85366,0.52219,0.87956,0.44116,0.89313,0.37815,0.48578,0.88735],"triangles":[49,4,5,3,4,49,47,0,48,46,32,47,45,31,46,28,43,42,6,49,5,48,49,6,7,47,48,46,47,9,45,44,30,44,43,29,48,6,7,45,46,10,47,7,8,44,45,11,9,47,8,46,9,10,50,40,41,14,50,41,14,41,42,15,50,14,13,14,42,13,42,43,11,45,10,43,44,12,12,13,43,44,11,12,2,3,49,23,24,25,0,1,48,33,23,25,35,34,25,33,25,34,32,0,47,25,36,35,37,25,38,25,37,36,38,25,39,31,32,46,25,40,39,26,40,25,30,31,45,41,40,26,42,27,28,26,27,41,29,30,44,28,29,43,22,23,33,22,33,34,35,21,22,35,22,34,20,21,35,20,35,36,19,20,36,18,19,36,18,36,37,17,18,37,17,37,38,17,38,16,16,38,39,15,39,40,41,27,42,50,15,40,15,16,39,1,2,49,48,1,49],"vertices":[39.32,89.58,65.12,87.35,87.48,82.1,106.52,71.62,119.49,57.26,124.46,41.81,122.01,-32.54,117.74,-40.96,111.4,-53.08,101.6,-66.31,91.34,-79.38,77.76,-88.52,56.47,-88.58,35.04,-88.19,10.71,-86.48,-25.6,-82.17,-41.41,-79.08,-62.39,-74.11,-78.95,-69.14,-93.3,-62.8,-104.78,-56.06,-114.27,-47.41,-122.83,-36.02,-123.09,21.85,-121.12,35.55,-107.76,48.22,-87.04,58.26,-63.25,63.23,-43.95,64.74,-26.23,63.67,-17.52,71.39,-3.58,79.98,14.45,86.69,-118.42,9.24,-106.12,-3.07,-89.44,-11.18,-74.16,-17.54,-58.59,-22.51,-42.12,-26.53,-22.08,-29.84,0.26,-32.16,24.83,-35.2,43.27,-35.75,62.03,-36,78.37,-35.75,91.07,-25.54,100.45,-15.32,109.28,-4.84,117.29,12.83,121.48,26.56,-4.39,-84.44]}},"5":{"5":{"x":82.19,"y":19.84,"rotation":-85.03,"width":181,"height":159}},"6":{"6":{"x":80.35,"y":21.97,"rotation":-95.44,"width":375,"height":375}},"7":{"3":{"type":"mesh","hull":40,"uvs":[0.747,0.0129,0.71535,0.1599,0.70626,0.1777,0.6957,0.18389,0.68029,0.18157,0.66083,0.18584,0.67628,0.19933,0.69314,0.21315,0.71285,0.23848,0.72615,0.26334,0.73442,0.29218,0.7374,0.33642,0.73953,0.35273,0.66098,0.3798,0.65761,0.37846,0.65995,0.35138,0.66022,0.31145,0.65697,0.28361,0.643,0.25535,0.61668,0.24487,0.58207,0.2496,0.55136,0.26344,0.5213,0.28529,0.49438,0.31357,0.47051,0.35487,0.45812,0.39728,0.45485,0.4373,0.41221,0.45332,0.37344,0.44731,0.36676,0.43988,0.37059,0.39262,0.37988,0.34337,0.39786,0.29678,0.4161,0.26119,0.44226,0.22642,0.47453,0.1932,0.49949,0.17195,0.43245,0.14213,0.4393,0,0.74557,0],"triangles":[36,39,0,39,36,38,36,37,38,5,36,0,5,0,1,2,4,1,3,4,2,1,4,5,5,20,36,19,20,5,18,19,5,18,5,6,18,6,7,21,36,20,35,36,21,17,18,7,17,7,8,17,8,9,22,35,21,34,35,22,10,16,17,10,17,9,23,34,22,33,34,23,16,10,11,15,16,11,15,11,12,24,33,23,32,33,24,31,32,24,13,15,12,14,15,13,25,31,24,30,31,25,25,27,30,28,29,30,30,27,28,25,26,27],"vertices":[56.32,94.98,49.1,66.32,47.03,62.85,44.62,61.64,41.11,62.09,36.67,61.26,40.19,58.63,44.04,55.94,48.53,51,51.56,46.15,53.45,40.53,54.13,31.9,54.61,28.72,36.7,23.44,35.93,23.7,36.47,28.98,36.53,36.77,35.79,42.2,32.6,47.71,26.6,49.75,18.71,48.83,11.71,46.13,4.86,41.87,-1.28,36.35,-6.72,28.3,-9.55,20.03,-10.29,12.23,-20.02,9.1,-28.86,10.27,-30.38,11.72,-29.51,20.94,-27.39,30.54,-23.29,39.63,-19.13,46.57,-13.17,53.35,-5.81,59.83,-0.12,63.97,-15.4,69.78,-13.84,97.5,55.99,97.5]}},"blast_12":{"blast_122":{"scaleX":7.9,"scaleY":7.9,"width":70,"height":70}},"blast_13":{"blast_132":{"scaleX":2,"scaleY":2,"width":160,"height":160}},"blast_14":{"blast_132":{"scaleX":2,"scaleY":2,"width":160,"height":160}},"blast_122":{"blast_122":{"width":70,"height":70}},"mj1212":{"mj1212":{"width":256,"height":256}},"mj1213":{"mj1212":{"width":256,"height":256}},"mj_4":{"mj_3":{"width":47,"height":46}},"mj_9":{"mj_3":{"width":47,"height":46}},"mj_10":{"mj_3":{"width":47,"height":46}},"mj_12":{"mj_12":{"scaleX":2,"scaleY":2,"width":265,"height":265}},"mj_13":{"mj_12":{"scaleX":2,"scaleY":2,"width":265,"height":265}},"mj_14":{"mj_3":{"width":47,"height":46}},"mj_15":{"mj_3":{"width":47,"height":46}},"mj_16":{"mj_3":{"width":47,"height":46}},"mj_17":{"mj_3":{"width":47,"height":46}},"mxg/1a":{"mxg/1a":{"width":150,"height":150}},"mxg/1a3":{"mxg/1a":{"width":150,"height":150}},"mxg/1a5":{"mxg/1a":{"width":150,"height":150}},"mxg/1a7":{"mxg/1a":{"width":150,"height":150}},"mxg/1a9":{"mxg/1a":{"width":150,"height":150}},"mxg/1a11":{"mxg/1a":{"width":150,"height":150}},"mxg/1a13":{"mxg/1a":{"width":150,"height":150}},"mxg/1a14":{"mxg/1a":{"width":150,"height":150}},"mxg/1a15":{"mxg/1a":{"width":150,"height":150}},"mxg/1a17":{"mxg/1a":{"width":150,"height":150}}}}],"animations":{"in":{"slots":{"3":{"color":[{"time":0.8667,"color":"ffffffff"},{"time":1.0333,"color":"ffffff00"}]},"4":{"color":[{"color":"ffffffff","curve":"stepped"},{"time":0.1,"color":"ffffff9c"},{"time":0.1333,"color":"ffffff7e"}],"attachment":[{"time":0.1333,"name":null}]},"5":{"color":[{"time":0.8667,"color":"ffffffff"},{"time":1.0333,"color":"ffffff00"}],"attachment":[{"time":0.1333,"name":null},{"time":0.1667,"name":"5"}]},"6":{"color":[{"time":0.8667,"color":"ffffffff"},{"time":1.0333,"color":"ffffff00"}],"attachment":[{"time":0.1,"name":"6"},{"time":0.1667,"name":null}]},"7":{"color":[{"color":"ffffff00"},{"time":0.2,"color":"ffffffa7"},{"time":0.3333,"color":"ffffff7a"},{"time":0.6333,"color":"ffffff00","curve":"stepped"},{"time":1.0333,"color":"ffffff00"}]},"blast_12":{"color":[{"color":"ff2929cf"},{"time":0.2667,"color":"ffffff00"}],"attachment":[{"name":"blast_122"}]},"blast_13":{"color":[{"color":"ff9999ff"},{"time":0.7333,"color":"ffffff00"}],"attachment":[{"name":"blast_132"}]},"blast_14":{"color":[{"color":"ff5959a2"},{"time":0.6,"color":"ffffff00"}],"attachment":[{"name":"blast_132"}]},"blast_122":{"color":[{"time":0.1,"color":"ffffffa4","curve":0.25,"c4":0.68},{"time":0.5667,"color":"ffffff00"}],"attachment":[{"time":0.1,"name":"blast_122"}]},"mj1212":{"color":[{"time":0.1,"color":"65faffaf","curve":0.997,"c4":0.96},{"time":0.4333,"color":"ffffff00"}],"attachment":[{"time":0.1,"name":"mj1212"}]},"mj1213":{"color":[{"time":0.1,"color":"65faffbd"},{"time":0.3,"color":"ffffff00"}],"attachment":[{"time":0.1,"name":"mj1212"}]},"mj_4":{"color":[{"time":0.8333,"color":"ffffffff"},{"time":1.0333,"color":"ffffff00"}],"attachment":[{"name":null},{"time":0.5667,"name":"mj_3"}]},"mj_9":{"color":[{"time":0.6667,"color":"ffffffff"},{"time":0.8,"color":"ffffff00"}],"attachment":[{"name":null},{"time":0.3,"name":"mj_3"}]},"mj_10":{"color":[{"time":0.2,"color":"ffffffb2","curve":"stepped"},{"time":0.6667,"color":"ffffffb2"},{"time":0.8,"color":"ffffff00"}],"attachment":[{"name":null},{"time":0.2,"name":"mj_3"}]},"mj_12":{"color":[{"color":"ff7d7dff"},{"time":0.3333,"color":"ff7d7d69"},{"time":0.8333,"color":"ff7d7d8e"},{"time":1,"color":"ff7d7d00"}]},"mj_13":{"color":[{"color":"ffffff6f"},{"time":0.3333,"color":"ffffff1f","curve":"stepped"},{"time":0.8333,"color":"ffffff1f"},{"time":1,"color":"ffffff00"}],"attachment":[{"name":"mj_12"}]},"mj_14":{"color":[{"time":0.8,"color":"ffffffff"},{"time":0.9,"color":"ffffff00"}],"attachment":[{"name":null},{"time":0.3667,"name":"mj_3"}]},"mj_15":{"color":[{"time":0.2333,"color":"ffffffff","curve":"stepped"},{"time":0.5333,"color":"ffffffff"},{"time":0.8,"color":"ffffff00"}],"attachment":[{"name":null},{"time":0.2333,"name":"mj_3"}]},"mj_16":{"color":[{"time":0.7333,"color":"ffffffff"},{"time":0.8,"color":"ffffff00"}],"attachment":[{"name":null},{"time":0.4,"name":"mj_3"}]},"mj_17":{"color":[{"time":0.8667,"color":"ffffffff"},{"time":1.0333,"color":"ffffff00"}],"attachment":[{"name":null},{"time":0.5333,"name":"mj_3"}]},"mxg/1a":{"color":[{"time":0.1333,"color":"ffffff00"},{"time":0.2,"color":"ffffffff","curve":"stepped"},{"time":0.6,"color":"ffffffff"},{"time":0.7667,"color":"ffffff00"}],"attachment":[{"time":0.1333,"name":"mxg/1a"}]},"mxg/1a3":{"color":[{"time":0.1,"color":"ffffff00"},{"time":0.1667,"color":"ffffffff","curve":"stepped"},{"time":0.2667,"color":"ffffffff"},{"time":0.5667,"color":"ffffff00"}],"attachment":[{"time":0.1,"name":"mxg/1a"}]},"mxg/1a5":{"color":[{"time":0.0667,"color":"ffffff00"},{"time":0.1333,"color":"ffffff71"},{"time":0.5,"color":"ffffffff","curve":"stepped"},{"time":0.7667,"color":"ffffffff"},{"time":0.9667,"color":"ffffff00"}],"attachment":[{"time":0.0667,"name":"mxg/1a"}]},"mxg/1a7":{"color":[{"time":0.1,"color":"ffffff00"},{"time":0.1667,"color":"ffffffff","curve":"stepped"},{"time":0.6,"color":"ffffffff"},{"time":0.7667,"color":"ffffff00"}],"attachment":[{"time":0.1,"name":"mxg/1a"}]},"mxg/1a9":{"color":[{"time":0.2333,"color":"ffffff00"},{"time":0.3333,"color":"ffffffff","curve":"stepped"},{"time":0.5667,"color":"ffffffff"},{"time":0.7667,"color":"ffffff00"}],"attachment":[{"time":0.2333,"name":"mxg/1a"}]},"mxg/1a11":{"color":[{"time":0.1667,"color":"ffffff00"},{"time":0.4333,"color":"ffffffff","curve":"stepped"},{"time":0.5333,"color":"ffffffff"},{"time":0.7333,"color":"ffffff00"}],"attachment":[{"time":0.1667,"name":"mxg/1a"}]},"mxg/1a13":{"color":[{"time":0.2333,"color":"ffffff00"},{"time":0.3,"color":"ffffffff","curve":"stepped"},{"time":0.5333,"color":"ffffffff"},{"time":0.7333,"color":"ffffff00"}],"attachment":[{"time":0.2333,"name":"mxg/1a"}]},"mxg/1a14":{"color":[{"time":0.2333,"color":"ffffff00"},{"time":0.4,"color":"ffffffff","curve":"stepped"},{"time":0.5667,"color":"ffffffff"},{"time":0.7,"color":"ffffff00"}],"attachment":[{"time":0.2333,"name":"mxg/1a"}]},"mxg/1a15":{"color":[{"time":0.2,"color":"ffffff00"},{"time":0.3667,"color":"ffffffa3","curve":"stepped"},{"time":0.8333,"color":"ffffffa3"},{"time":0.9667,"color":"ffffff00"}],"attachment":[{"time":0.2,"name":"mxg/1a"}]},"mxg/1a17":{"color":[{"time":0.1,"color":"ffffff00"},{"time":0.2333,"color":"ffffffff","curve":"stepped"},{"time":0.3667,"color":"ffffffff"},{"time":0.5667,"color":"ffffff00"}],"attachment":[{"time":0.1,"name":"mxg/1a"}]}},"bones":{"5":{"rotate":[{"time":0.1667,"angle":-0.05},{"time":0.2667}],"scale":[{"time":0.1667,"x":1.133,"y":1.016},{"time":0.2667}],"shear":[{"time":0.1667,"x":-1.04,"y":-3.01},{"time":0.2667}]},"light":{"scale":[{"curve":0,"c2":0.43,"c3":0.75},{"time":0.6,"x":2.6,"y":2.6}]},"lizi3":{"translate":[{"time":0.0667,"x":6.45,"y":-5.88}],"scale":[{"time":0.0667,"x":0,"y":0},{"time":0.3333,"x":0.981,"y":0.981},{"time":0.5667,"x":0.2,"y":0.2},{"time":0.8333,"x":0.8,"y":0.8},{"time":1.0333,"x":0.3,"y":0.3}]},"lizi5":{"rotate":[{"time":0.3},{"time":0.8,"angle":22.6}],"translate":[{"time":0.3,"x":77.35,"y":28.67}],"scale":[{"time":0.3,"x":0,"y":0,"curve":0,"c2":0.41,"c3":0.75},{"time":0.5,"x":2.432,"y":2.432,"curve":0.25,"c4":0.64},{"time":0.8,"x":0.3,"y":0.3}]},"bone":{"rotate":[{},{"time":1.0333,"angle":-76.77}],"scale":[{"x":0.682,"y":0.682},{"time":0.1,"x":1.171,"y":1.171}]},"lizi6":{"translate":[{"time":0.3667,"x":93.48,"y":-88.03}],"scale":[{"time":0.3667,"x":0.5,"y":0.5,"curve":0,"c2":0.41,"c3":0.75},{"time":0.6333,"x":1.157,"y":1.157,"curve":0.25,"c4":0.64},{"time":0.9,"x":0.3,"y":0.3}]},"lizi7":{"translate":[{"time":0.2333,"x":95.04,"y":-203.32}],"scale":[{"time":0.2333,"x":0.5,"y":0.5,"curve":0,"c2":0.41,"c3":0.75},{"time":0.5333,"x":1.242,"y":1.242,"curve":0.25,"c4":0.64},{"time":0.8,"x":0.3,"y":0.3}]},"lizi8":{"translate":[{"time":0.4,"x":30.18,"y":23.38}],"scale":[{"time":0.4,"x":0.353,"y":0.353,"curve":0,"c2":0.41,"c3":0.75},{"time":0.6,"x":0.752,"y":0.752,"curve":0.25,"c4":0.64},{"time":0.8,"x":0.153,"y":0.153}]},"eff2":{"scale":[{"x":0.51,"y":0.51},{"time":0.1}]},"lizi9":{"rotate":[{"time":0.5333},{"time":1.0333,"angle":-12.32}],"translate":[{"time":0.5333,"x":58.76,"y":-70.03}],"scale":[{"time":0.5333,"x":0,"y":0,"curve":0,"c2":0.41,"c3":0.75},{"time":0.7667,"x":0.54,"y":0.54,"curve":0.25,"c4":0.64},{"time":1.0333,"x":0,"y":0}]},"yf2":{"rotate":[{"time":0.1333,"angle":-114.03},{"time":0.7667,"angle":-85.86}],"translate":[{"time":0.1333,"x":-4.96,"y":-69.43},{"time":0.7667,"x":-5.18,"y":92.72}],"scale":[{"time":0.1333,"x":0.875,"y":0.875}]},"yf3":{"rotate":[{"time":0.1,"angle":26.03},{"time":0.5667,"angle":-26.4}],"translate":[{"time":0.1,"x":-20.69,"y":-64.3},{"time":0.5667,"x":-20.69,"y":-9.63}],"scale":[{"time":0.1,"x":0.672,"y":0.672}]},"yf4":{"rotate":[{"time":0.0667,"angle":-138.68},{"time":0.9667,"angle":-74.24}],"translate":[{"time":0.0667,"x":-256.69,"y":-194.68},{"time":0.9667,"x":-256.69,"y":-56.94}],"scale":[{"time":0.0667,"x":0.777,"y":0.777,"curve":"stepped"},{"time":0.5,"x":0.777,"y":0.777},{"time":0.9667,"x":0.459,"y":0.459}]},"yf5":{"rotate":[{"time":0.1},{"time":0.7667,"angle":-95.12}],"translate":[{"time":0.1,"x":-140,"y":-261.97},{"time":0.7667,"x":-140,"y":-133.25}],"scale":[{"time":0.1}]},"yf6":{"rotate":[{"time":0.2333,"angle":-162.11},{"time":0.7667,"angle":152.8}],"translate":[{"time":0.2333,"x":117.01,"y":-138.16},{"time":0.7667,"x":113.31,"y":2.46}],"scale":[{"time":0.2333,"x":0.723,"y":0.723}]},"yf7":{"rotate":[{"time":0.1667,"angle":-49.97},{"time":0.9,"angle":-120.65}],"translate":[{"time":0.1667,"x":52.63,"y":-185.6},{"time":0.9,"x":52.63,"y":-67.99}],"scale":[{"time":0.1667,"x":0.759,"y":0.759}]},"yf8":{"rotate":[{"time":0.2333,"angle":-118.93},{"time":0.9667,"angle":-72.34}],"translate":[{"time":0.2333,"x":-200.5,"y":-257.24},{"time":0.9667,"x":-200.5,"y":-148.51}],"scale":[{"time":0.2333,"x":0.629,"y":0.629}]},"yf9":{"rotate":[{"time":0.2,"angle":-149.65},{"time":0.9667,"angle":165.99}],"translate":[{"time":0.2,"x":-9.89,"y":-371.32},{"time":0.9667,"x":-7.88,"y":-245.31}],"scale":[{"time":0.2,"x":1.434,"y":1.434}]},"yf10":{"rotate":[{"time":0.1},{"time":0.7333,"angle":-26.4}],"translate":[{"time":0.1,"x":-243.71,"y":-46.68},{"time":0.7333,"x":-239.58,"y":80.17}],"scale":[{"time":0.1}]},"zong":{"translate":[{"curve":"stepped"},{"time":0.2},{"time":0.3667,"y":-32.9}],"scale":[{"x":0.6,"y":0.6,"curve":0,"c2":0.29,"c3":0.531},{"time":0.2,"x":1.23,"y":1.23,"curve":0.25,"c4":0.9},{"time":0.3667,"x":0.95,"y":0.95,"curve":0.25,"c3":0.75},{"time":0.5333}]},"bone3":{"scale":[{"time":0.1,"x":0.875,"y":0.956},{"time":0.1667,"x":0.996,"y":0.956}],"shear":[{"time":0.1,"x":-28.61,"y":1.01},{"time":0.1667,"x":-10.01,"y":1.01}]},"hou":{"translate":[{"time":0.1667,"curve":"stepped"},{"time":0.2667}]},"yf":{"rotate":[{"angle":180}],"translate":[{"time":0.1,"y":49.5}],"scale":[{"time":0.1,"x":0.2,"y":0.2,"curve":0,"c2":0.26,"c3":0.75},{"time":0.4333,"x":1.095,"y":1.095},{"time":0.6333,"x":1.124,"y":1.124}]},"yf11":{"rotate":[{"time":0.2333,"angle":163.51},{"time":0.8333,"angle":-145.7}],"translate":[{"time":0.2333,"x":-114.2,"y":56.77},{"time":0.8333,"x":-114.2,"y":165.5}],"scale":[{"time":0.2333,"x":0.629,"y":0.629}]},"lizi10":{"translate":[{"time":0.2,"x":-69.59,"y":-50.63}],"scale":[{"time":0.2,"x":0,"y":0,"curve":0,"c2":0.41,"c3":0.75},{"time":0.5,"x":0.867,"y":0.867,"curve":0.25,"c4":0.64},{"time":0.8,"x":0.3,"y":0.3}]},"xia2":{"translate":[{"time":0.1,"x":19.44,"y":73.55}],"scale":[{"time":0.1,"x":0.62,"y":0.62}],"shear":[{"time":0.1,"x":-17.98,"y":-47.44},{"time":0.6}]},"xia3":{"translate":[{"time":0.1,"x":17.88,"y":81.09}],"scale":[{"time":0.1,"x":1.179,"y":1.179}]},"xia4":{"rotate":[{"time":0.1,"angle":-136.93}],"translate":[{"time":0.1,"x":15.98,"y":82.01}],"scale":[{"time":0.1,"y":0.488}],"shear":[{"time":0.1,"x":-17.98,"y":-47.44},{"time":0.5}]},"bone2":{"scale":[{"x":0.75,"y":0.75}]},"hou2":{"translate":[{"x":3.72,"y":-16.12}]}},"deform":{"default":{"4":{"4":[{},{"time":0.0333,"vertices":[-0.528,1.18799,-0.39598,3.29998,0.79199,6.46798,0.528,9.76796,0.39601,12.40795,-1.58398,3.95996,0,16.73997,0,10.25999,0,11.33997,0,9.44998,0,11.60999,0,13.22998,0,9.18,0,7.55999,0,5.67,0,4.58999,0,4.85997,0,3.51,0,2.43001,0,0,0,0.81001,0,1.88999,0,1.35,0,0,0,0,0,0,0,0,0,0,0,0,0,0,0,0,0,0,0,0,0,0,0,1.35,0,1.88999,0,3.24001,0,3.51,0,4.85997,0,4.58999,0,4.86,0,5.67,0,7.55999,0,9.18,0,13.22998,0,11.60999,0,9.44998,0,11.33997,0,10.25999,-0.132,12.80395,0,4.86]},{"time":0.1,"vertices":[-5.41199,13.24394,-1.51595,25.00694,-6.80296,34.30792,-17.74799,45.16798,-26.83193,58.37087,-15.84497,28.95992,-13.02002,98.61191,-9.01805,102.89984,-6.11792,107.98689,-1.44801,113.26889,-3.26398,107.03988,-3.67401,105.90192,-1.005,100.01984,-1.584,91.10396,3.04696,82.32297,4.35098,67.01495,0.56693,59.99195,5.48998,50.02593,7.37197,41.697,7.70499,33.93597,6.55401,25.77294,2.18802,16.04195,0.49599,7.46198,-15.75998,6.74197,-12.80392,-1.66001,-6.98997,-3.22698,0.29097,-0.899,-0.05201,1.66699,-3.16898,6.15598,-3.399,13.69298,-1.71899,9.61198,0.09599,7.99696,-0.96798,7.89697,-13.467,18.05405,-11.35503,33.51601,-10.58398,45.13197,-14.50498,54.38097,-15.804,63.58804,-18.55803,71.748,-21.07506,80.59895,-29.47903,87.817,-36.682,96.18802,-36.391,103.731,-35.43798,111.84804,-32.18398,118.63992,-31.26897,115.25387,-26.9759,112.73891,-27.76598,107.12084,-28.7809,95.33381,-28.55194,86.83685,-0.55006,75.16286]}]}}}}}}