{"skeleton":{"hash":"JZve+WUEpw5RSxyfTAyF3y50x7g","spine":"3.8.99","x":-122,"y":-10,"width":244,"height":146},"bones":[{"name":"root"},{"name":"xiaobaoxiang4","parent":"root","length":53.09,"rotation":90},{"name":"hook_num_1","parent":"xiaobaoxiang4","x":41,"y":46},{"name":"hook_num_2","parent":"xiaobaoxiang4","x":41,"y":-53},{"name":"hook_icon_2","parent":"xiaobaoxiang4","x":92,"y":-53},{"name":"hook_icon_1","parent":"xiaobaoxiang4","x":92,"y":46}],"slots":[{"name":"daojutishi","bone":"xiaobaoxiang4","attachment":"tip_bg"},{"name":"slot_icon_1","bone":"hook_icon_1"},{"name":"slot_icon_2","bone":"hook_icon_2"},{"name":"slot_num_1","bone":"hook_num_1"},{"name":"slot_num_2","bone":"hook_num_2"}],"skins":[{"name":"default","attachments":{"daojutishi":{"tip_bg":{"x":63,"rotation":-90,"width":244,"height":146}}}}],"events":{"event_rewards":{}},"animations":{"in":{"slots":{"daojutishi":{"color":[{"color":"ffffff00"},{"time":0.1667,"color":"ffffffff"}]},"slot_icon_1":{"color":[{"color":"ffffff00"},{"time":0.1667,"color":"ffffffff"}]},"slot_icon_2":{"color":[{"color":"ffffff00"},{"time":0.1667,"color":"ffffffff"}]},"slot_num_1":{"color":[{"color":"ffffff00"},{"time":0.1667,"color":"ffffffff"}]},"slot_num_2":{"color":[{"color":"ffffff00"},{"time":0.1667,"color":"ffffffff"}]}},"bones":{"xiaobaoxiang4":{"scale":[{"x":0.5,"y":0.5,"curve":0.25,"c3":0.75},{"time":0.1667,"x":1.1,"y":1.1,"curve":0.25,"c3":0.75},{"time":0.2667}]}},"events":[{"name":"event_rewards"}]},"init":{},"out":{"slots":{"daojutishi":{"color":[{"color":"ffffffff"},{"time":0.1,"color":"ffffff00"}]},"slot_icon_1":{"color":[{"color":"ffffffff"},{"time":0.1,"color":"ffffff00"}]},"slot_icon_2":{"color":[{"color":"ffffffff"},{"time":0.1,"color":"ffffff00"}]},"slot_num_1":{"color":[{"color":"ffffffff"},{"time":0.1,"color":"ffffff00"}]},"slot_num_2":{"color":[{"color":"ffffffff"},{"time":0.1,"color":"ffffff00"}]}},"bones":{"xiaobaoxiang4":{"scale":[{},{"time":0.1,"x":0.6,"y":0.6}]}}}}}